L7N/L7N.py
L7N/__init__.py
L7N-0.5.dist-info/LICENSE.txt
L7N-0.5.dist-info/METADATA
L7N-0.5.dist-info/WHEEL
L7N-0.5.dist-info/top_level.txt
L7N-0.5.dist-info/RECORD
