Metadata-Version: 2.1
Name: L7N
Version: 0.5
Summary: Module By @g_4_q In telegram 
Author: Programmer L7N - Fahal 
Classifier: Programming Language :: Python :: 3
Classifier: Operating System :: OS Independent
Classifier: License :: OSI Approved :: MIT License
License-File: LICENSE.txt
